joplan/__init__.py
joplan/utils.py
joplan-0.1.0.dist-info/LICENSE
joplan-0.1.0.dist-info/WHEEL
joplan-0.1.0.dist-info/METADATA
joplan-0.1.0.dist-info/RECORD
